xlayers.libs/libgfortran-2bbace53.so.4.0.0
xlayers.libs/libquadmath-af029652.so.0.0.0
xlayers-0.2.2.dist-info/RECORD
xlayers-0.2.2.dist-info/WHEEL
xlayers-0.2.2.dist-info/top_level.txt
xlayers-0.2.2.dist-info/METADATA
xlayers-0.2.2.dist-info/LICENSE
xlayers/fine.py
xlayers/layers.cpython-38-i386-linux-gnu.so
xlayers/test_fine.py
xlayers/finegrid.cpython-38-i386-linux-gnu.so
xlayers/__init__.py
xlayers/_version.py
xlayers/core.py
