Metadata-Version: 1.1
Name: xlayers
Version: 0.2.2
Summary: Fast convective parameters for numpy, dask, and xarray
Home-page: https://github.com/cspencerjones/xlayers
Author: xlayers Developers
Author-email: spencerj@ldeo.columbia.edu
License: MIT
Platform: UNKNOWN
Classifier: Development Status :: 4 - Beta
Classifier: License :: OSI Approved :: Apache Software License
Classifier: Operating System :: OS Independent
Classifier: Intended Audience :: Science/Research
Classifier: Programming Language :: Python
Classifier: Programming Language :: Python :: 3
Classifier: Programming Language :: Python :: 3.6
Classifier: Topic :: Scientific/Engineering
